concepts/__init__.py
concepts/admin.py
concepts/apps.py
concepts/forms.py
concepts/managers.py
concepts/models.py
concepts/parsers.py
concepts/settings.py
concepts/tests.py
concepts/urls.py
concepts/views.py
concepts/widgets.py
concepts/migrations/0001_initial.py
concepts/migrations/0002_add_category_geometry.py
concepts/migrations/__init__.py
concepts/static/.DS_Store
concepts/static/concepts/.DS_Store
concepts/static/concepts/horizontalradio.css
concepts/static/concepts/jquery-textext-min.js
concepts/static/concepts/jquery-textext.js
concepts/static/concepts/textext.css
concepts/templates/.DS_Store
concepts/templates/admin/.DS_Store
concepts/templates/admin/concepts/change_form.html
concepts/templates/concepts/.DS_Store
concepts/templates/concepts/autocomplete.html
concepts/templates/concepts/textext.html
concepts/templatetags/__init__.py
concepts/templatetags/concept_related_items.py
concepts/templatetags/concepts_tags.py
django_concepts-0.7.2.dist-info/DESCRIPTION.rst
django_concepts-0.7.2.dist-info/METADATA
django_concepts-0.7.2.dist-info/RECORD
django_concepts-0.7.2.dist-info/WHEEL
django_concepts-0.7.2.dist-info/metadata.json
django_concepts-0.7.2.dist-info/pbr.json
django_concepts-0.7.2.dist-info/top_level.txt
