Metadata-Version: 2.0
Name: django-concepts
Version: 0.7.2
Summary: django-concepts
Home-page: http://github.com/callowayproject
Author: coordt
Author-email: coreyoordt@gmail.com
License: UNKNOWN
Platform: UNKNOWN
Classifier: License :: OSI Approved :: Apache Software License
Classifier: Framework :: Django
Requires-Dist: django-taggit (>=0.13)
